[
  {
    "periodo": "2026-07",
    "monto": "50000",
    "descripcion": "Mensualidad julio",
    "parcela_id": "a55aed58-5052-4df1-82a6-e41668167d21"
  },
  {
    "periodo": "2026-07",
    "monto": "50000",
    "descripcion": "Pago Juan Pérez",
    "parcela_id": "6c26d188-8f57-4ac6-8057-ceea44694dd4"
  },
  {
    "periodo": "2026-07",
    "monto": "50000",
    "descripcion": "Pago María López",
    "parcela_id": "b5a83343-a7e6-4503-8548-1656e473421c"
  },
  {
    "periodo": "2026-07",
    "monto": "50000",
    "descripcion": "Pago Carlos Silva",
    "parcela_id": "74eaa0b9-7572-48da-b07b-09567ce2167d"
  },
  {
    "periodo": "2026-07",
    "monto": "50000",
    "descripcion": "Pago Ana Martínez",
    "parcela_id": "f52f5736-2eae-4ce9-b38b-a448966960f6"
  },
  {
    "periodo": "2026-07",
    "monto": "50000",
    "descripcion": "Pago Pedro Rojas",
    "parcela_id": "162ba5cb-425f-4f7f-97e2-686e38fd0559"
  },
  {
    "periodo": "2026-07",
    "monto": "50000",
    "descripcion": "Pago Laura Torres",
    "parcela_id": "a9285211-14e4-4f97-81cb-bc2a749626f2"
  },
  {
    "periodo": "2026-07",
    "monto": "50000",
    "descripcion": "Pago Sofía Herrera",
    "parcela_id": "139f7b49-6d8c-47e5-b60a-316787c4e38d"
  },
  {
    "periodo": "2026-07",
    "monto": "50000",
    "descripcion": "Pago Miguel Ángel Ruiz",
    "parcela_id": "781f0a38-011d-4340-b211-6ec61fa714ba"
  },
  {
    "periodo": "2026-07",
    "monto": "50000",
    "descripcion": "Pago Valentina Muñoz",
    "parcela_id": "91391efe-da6b-423e-9977-53fd2d9266bf"
  },
  {
    "periodo": "2026-07",
    "monto": "50000",
    "descripcion": "Pago Santiago Vega",
    "parcela_id": "adbd4059-fc7c-419c-b4aa-39a53ab58bd3"
  },
  {
    "periodo": "2026-07",
    "monto": "50000",
    "descripcion": "Pago Isabel Guerrero",
    "parcela_id": "ba2fce15-547c-446a-9cdc-908de58d79a3"
  },
  {
    "periodo": "2026-07",
    "monto": "50000",
    "descripcion": "Pablo Castillo pendiente",
    "parcela_id": "4846156f-c303-4f8a-99a0-46537c90185a"
  },
  {
    "periodo": "2026-06",
    "monto": "50000",
    "descripcion": "Pago junio Juan Pérez",
    "parcela_id": "6c26d188-8f57-4ac6-8057-ceea44694dd4"
  },
  {
    "periodo": "2026-06",
    "monto": "50000",
    "descripcion": "Pago junio María López",
    "parcela_id": "b5a83343-a7e6-4503-8548-1656e473421c"
  },
  {
    "periodo": "2026-06",
    "monto": "50000",
    "descripcion": "Pago junio Carlos Silva",
    "parcela_id": "74eaa0b9-7572-48da-b07b-09567ce2167d"
  },
  {
    "periodo": "2026-06",
    "monto": "50000",
    "descripcion": "Pago junio Ana Martínez",
    "parcela_id": "f52f5736-2eae-4ce9-b38b-a448966960f6"
  },
  {
    "periodo": "2026-06",
    "monto": "50000",
    "descripcion": "Pago junio Pedro Rojas",
    "parcela_id": "162ba5cb-425f-4f7f-97e2-686e38fd0559"
  },
  {
    "periodo": "2026-06",
    "monto": "50000",
    "descripcion": "Pago junio Sofía Herrera",
    "parcela_id": "139f7b49-6d8c-47e5-b60a-316787c4e38d"
  },
  {
    "periodo": "2026-06",
    "monto": "50000",
    "descripcion": "Pago junio Valentina Muñoz",
    "parcela_id": "91391efe-da6b-423e-9977-53fd2d9266bf"
  },
  {
    "periodo": "2026-06",
    "monto": "50000",
    "descripcion": "Pago junio Isabel Guerrero",
    "parcela_id": "ba2fce15-547c-446a-9cdc-908de58d79a3"
  },
  {
    "periodo": "2026-06",
    "monto": "15000",
    "descripcion": "Pago fondo reserva Juan Pérez",
    "parcela_id": "6c26d188-8f57-4ac6-8057-ceea44694dd4"
  },
  {
    "periodo": "2026-06",
    "monto": "15000",
    "descripcion": "Pago fondo reserva Carlos Silva",
    "parcela_id": "74eaa0b9-7572-48da-b07b-09567ce2167d"
  },
  {
    "periodo": "2026-06",
    "monto": "15000",
    "descripcion": "Pago fondo reserva Laura Torres",
    "parcela_id": "a55aed58-5052-4df1-82a6-e41668167d21"
  },
  {
    "periodo": "2026-06",
    "monto": "15000",
    "descripcion": "Pago fondo reserva Miguel Ángel Ruiz",
    "parcela_id": "781f0a38-011d-4340-b211-6ec61fa714ba"
  },
  {
    "periodo": "2026-06",
    "monto": "15000",
    "descripcion": "Pago fondo reserva Santiago Vega",
    "parcela_id": "adbd4059-fc7c-419c-b4aa-39a53ab58bd3"
  },
  {
    "periodo": "2026-06",
    "monto": "15000",
    "descripcion": "Pago fondo reserva Pablo Castillo",
    "parcela_id": "4846156f-c303-4f8a-99a0-46537c90185a"
  },
  {
    "periodo": "2026-07",
    "monto": "25000",
    "descripcion": "Reparación pileta",
    "parcela_id": null
  }
]
